mlflow/__init__.py
mlflow/data.py
mlflow/db.py
mlflow/exceptions.py
mlflow/experiments.py
mlflow/mleap.py
mlflow/runs.py
mlflow/version.py
mlflow/entities/__init__.py
mlflow/entities/_mlflow_object.py
mlflow/entities/experiment.py
mlflow/entities/experiment_tag.py
mlflow/entities/file_info.py
mlflow/entities/lifecycle_stage.py
mlflow/entities/metric.py
mlflow/entities/param.py
mlflow/entities/run.py
mlflow/entities/run_data.py
mlflow/entities/run_info.py
mlflow/entities/run_status.py
mlflow/entities/run_tag.py
mlflow/entities/source_type.py
mlflow/entities/view_type.py
mlflow/entities/model_registry/__init__.py
mlflow/entities/model_registry/_model_registry_entity.py
mlflow/entities/model_registry/model_version.py
mlflow/entities/model_registry/model_version_stages.py
mlflow/entities/model_registry/model_version_status.py
mlflow/entities/model_registry/model_version_tag.py
mlflow/entities/model_registry/registered_model.py
mlflow/entities/model_registry/registered_model_tag.py
mlflow/models/__init__.py
mlflow/models/docker_utils.py
mlflow/models/flavor_backend.py
mlflow/models/flavor_backend_registry.py
mlflow/models/model.py
mlflow/models/signature.py
mlflow/models/utils.py
mlflow/models/container/__init__.py
mlflow/protos/__init__.py
mlflow/protos/databricks_artifacts_pb2.py
mlflow/protos/databricks_pb2.py
mlflow/protos/model_registry_pb2.py
mlflow/protos/service_pb2.py
mlflow/protos/scalapb/__init__.py
mlflow/protos/scalapb/scalapb_pb2.py
mlflow/store/__init__.py
mlflow/store/db/__init__.py
mlflow/store/db/base_sql_model.py
mlflow/store/db/db_types.py
mlflow/store/db/utils.py
mlflow/store/db_migrations/__init__.py
mlflow/store/db_migrations/env.py
mlflow/store/db_migrations/versions/0a8213491aaa_drop_duplicate_killed_constraint.py
mlflow/store/db_migrations/versions/181f10493468_allow_nulls_for_metric_values.py
mlflow/store/db_migrations/versions/27a6a02d2cf1_add_model_version_tags_table.py
blind-0.0.1.dist-info/LICENSE.txt
blind-0.0.1.dist-info/METADATA
blind-0.0.1.dist-info/WHEEL
blind-0.0.1.dist-info/top_level.txt
blind-0.0.1.dist-info/RECORD
