Metadata-Version: 2.1
Name: blind
Version: 0.0.1
Summary: Blind Client: The easiest ML tracking library
Home-page: http://google.com
Author: Jake
License: Apache License 2.0
Keywords: ml ai tracking mlops
Platform: UNKNOWN
Classifier: Intended Audience :: Developers
Classifier: Programming Language :: Python :: 3.8
Requires-Python: >=3.6
License-File: LICENSE.txt
Requires-Dist: click
Requires-Dist: cloudpickle
Requires-Dist: entrypoints
Requires-Dist: gitpython
Requires-Dist: pyyaml
Requires-Dist: protobuf
Requires-Dist: pytz
Requires-Dist: requests
Requires-Dist: Flask
Requires-Dist: gunicorn
Requires-Dist: cython
Requires-Dist: numpy
Requires-Dist: pandas
Requires-Dist: querystring-parser
Requires-Dist: sqlparse
Requires-Dist: sqlalchemy
